MANIFEST.in
README.md
setup.cfg
setup.py
docoskin/__init__.py
docoskin/defaults.py
docoskin/docoskin.py
docoskin/dummythreadpoolexecutor.py
docoskin/exceptions.py
docoskin/image_operations.py
docoskin/version.py
docoskin/warping.py
docoskin.egg-info/PKG-INFO
docoskin.egg-info/SOURCES.txt
docoskin.egg-info/dependency_links.txt
docoskin.egg-info/entry_points.txt
docoskin.egg-info/requires.txt
docoskin.egg-info/top_level.txt
tests/conftest.py
tests/test_full_pipeline.py
tests/test_homography.py
tests/test_stretched_contrast.py
tests/test_warp_coverage.py
tests/utils.py