Metadata-Version: 2.1
Name: docoskin
Version: 0.1.0
Summary: "Onion-skin" visual differences between a reference document image and a scanned copy
Home-page: https://github.com/risicle/docoskin
Author: Robert Scott
Author-email: code@humanleg.org.uk
License: GPLv3
Keywords: document scan compare visual diff signature
Platform: UNKNOWN
Classifier: Development Status :: 3 - Alpha
Classifier: Intended Audience :: Developers
Classifier: Intended Audience :: Legal Industry
Classifier: Topic :: Multimedia :: Graphics :: Viewers
Classifier: License :: OSI Approved :: GNU General Public License v3 (GPLv3)
Classifier: Programming Language :: Python :: 2
Classifier: Programming Language :: Python :: 2.7
Classifier: Programming Language :: Python :: 3
Classifier: Programming Language :: Python :: 3.5
Provides-Extra: pypi_opencv
